putz/__init__.py
putz/putz.py
putz/version.py
putz/cli/__init__.py
putz/cli/main.py
putz-1.0.1.dist-info/COPYING
putz-1.0.1.dist-info/METADATA
putz-1.0.1.dist-info/WHEEL
putz-1.0.1.dist-info/entry_points.txt
putz-1.0.1.dist-info/top_level.txt
putz-1.0.1.dist-info/RECORD
