Metadata-Version: 2.1
Name: putz
Version: 1.0.1
Summary: A module for putzing around with Python.
Home-page: https://github.com/axfelix/putz
Author: Alex Garnett
Author-email: axfelix@gmail.com
License: MIT
Platform: UNKNOWN
Requires-Python: >3.5.0
Requires-Dist: setuptools
Requires-Dist: docopt
Requires-Dist: pypi-search
